smartypants.py
smartypants-2.0.0.dist-info/RECORD
smartypants-2.0.0.dist-info/METADATA
smartypants-2.0.0.dist-info/metadata.json
smartypants-2.0.0.dist-info/DESCRIPTION.rst
smartypants-2.0.0.dist-info/WHEEL
smartypants-2.0.0.data/scripts/smartypants
