Metadata-Version: 1.1
Name: smartypants
Version: 2.0.0
Summary: Python with the SmartyPants
Home-page: https://bitbucket.org/livibetter/smartypants.py
Author: Yu-Jie Lin
Author-email: livibetter@gmail.com
License: BSD License
Platform: UNKNOWN
Classifier: Development Status :: 5 - Production/Stable
Classifier: Intended Audience :: Developers
Classifier: Intended Audience :: End Users/Desktop
Classifier: License :: OSI Approved :: BSD License
Classifier: Operating System :: OS Independent
Classifier: Programming Language :: Python :: 2
Classifier: Programming Language :: Python :: 3
Classifier: Topic :: Text Processing :: Filters
